browser_use/__init__.py
browser_use/utils.py
browser_use/browser/browser.py
browser_use/browser/context.py
browser_use/browser/views.py
browser_use/browser/tests/screenshot_test.py
browser_use/browser/tests/test_clicks.py
browser_use/controller/views.py
browser_use/dom/__init__.py
browser_use/dom/buildDomTree.js
browser_use/dom/service.py
browser_use/dom/views.py
browser_use/dom/history_tree_processor/service.py
browser_use/dom/history_tree_processor/view.py
browser_use/dom/tests/debug_page_structure.py
browser_use/dom/tests/extraction_test.py
browser_use/dom/tests/process_dom_test.py
mcp_server/__init__.py
mcp_server/mcp_server.py
mcp_browser_use_tools-0.1.6.dist-info/METADATA
mcp_browser_use_tools-0.1.6.dist-info/WHEEL
mcp_browser_use_tools-0.1.6.dist-info/entry_points.txt
mcp_browser_use_tools-0.1.6.dist-info/top_level.txt
mcp_browser_use_tools-0.1.6.dist-info/RECORD
