Metadata-Version: 2.2
Name: mcp-browser-use-tools
Version: 0.1.6
Summary: This package vendors a subset of [browser-use](https://github.com/browser-use/browser-use) with minimal dependencies exposed as an mcp-server.
Requires-Python: >=3.11
Requires-Dist: fastmcp>=0.4.1
Requires-Dist: playwright>=1.50.0
